streamlit_change_language
