Metadata-Version: 2.1
Name: streamlit-change-language
Version: 0.0.2
Summary: 支持streamlit内置组件中的文本中英文切换
Home-page: 
Author: py_yzy
Author-email: 3215574613@qq.com
Requires-Python: >=3.9
License-File: LICENSE
Requires-Dist: streamlit>=1.38.0
Requires-Dist: configparser
